


[

{"registration_no":692917,"timestamp":"2015-05-06T17:07:57.954024","notice":"","coded_name":"HCSELANAUJ","type":"PA(B)","county":0,"date":"2010-12-09","remainder_name":"","complex_name":"","hex_code":"C5","address":"94 BROOKE FORD NU66 2MQ ELECTASHIRE","occupation":"(N/A) AROMATHERAPIST","county_text":"","court_info":"LAKE ZIONBOROUGH COUNTY COURT 609 OF 2015","property":"","parish":"","notice_refs":""},{"registration_no":120682,"timestamp":"2015-09-17T05:58:53.681138","notice":"","coded_name":"REROBYMMIT","type":"PA(B)","county":0,"date":"2011-06-08","remainder_name":"","complex_name":"","hex_code":"C5","address":"509 NAOMI RUN SX34 5KO NORTH CHESTER","occupation":"(N/A) SPECIAL CONSTABLE","county_text":"","court_info":"EAST CURTTON COUNTY COURT 390 OF 2015","property":"","parish":"","notice_refs":""},{"registration_no":226638,"timestamp":"2015-01-17T17:22:10.355554","notice":"","coded_name":"SSOKNERMAC","type":"PA(B)","county":0,"date":"2011-06-12","remainder_name":"","complex_name":"","hex_code":"C6","address":"319 BAILEY CENTERS WH23 9RV WILKINSONBOROUGH","occupation":"(N/A) ARCHAEOLOGIST","county_text":"","court_info":"LAKE APRIL COUNTY COURT 469 OF 2015","property":"","parish":"","notice_refs":""},{"registration_no":862632,"timestamp":"2015-09-13T00:57:10.500261","notice":"","coded_name":"SSOKNERMAC","type":"WO(B)","county":0,"date":"2011-06-29","remainder_name":"","complex_name":"","hex_code":"C6","address":"319 BAILEY CENTERS WH23 9RV WILKINSONBOROUGH","occupation":"(N/A) ARCHAEOLOGIST","county_text":"","court_info":"LAKE APRIL COUNTY COURT 469 OF 2015","property":"","parish":"","notice_refs":""},{"registration_no":907638,"timestamp":"2015-02-15T22:53:05.520025","notice":"","coded_name":"ENWOTNOTWEN","type":"PA(B)","county":0,"date":"2011-04-18","remainder_name":"","complex_name":"","hex_code":"C6","address":"58 LEUSCHKE ROW CA33 3CP NEW HILLARD  215 KOHLER LAKE FS15 9UB PORT TOM","occupation":"(N/A) MACHINIST T/A MATDAX","county_text":"","court_info":"WEST DAHLIATOWN COUNTY COURT 751 OF 2015","property":"","parish":"","notice_refs":""},{"registration_no":711463,"timestamp":"2015-04-04T23:59:44.566711","notice":"","coded_name":"ENWOTNOTWEN","type":"WO(B)","county":0,"date":"2011-05-07","remainder_name":"","complex_name":"","hex_code":"C6","address":"58 LEUSCHKE ROW CA33 3CP NEW HILLARD  215 KOHLER LAKE FS15 9UB PORT TOM","occupation":"(N/A) MACHINIST T/A MATDAX","county_text":"","court_info":"WEST DAHLIATOWN COUNTY COURT 751 OF 2015","property":"","parish":"","notice_refs":""},{"registration_no":720268,"timestamp":"2015-03-18T22:18:51.465266","notice":"","coded_name":"NESNAHIGIULE","type":"PA(B)","county":0,"date":"2011-11-15","remainder_name":"CATHARIN","complex_name":"","hex_code":"29C5","address":"31 LEDNER COURT YK95 5CL WEST VELMA","occupation":"(N/A) MINER","county_text":"","court_info":"WEST MYLENELAND COUNTY COURT 499 OF 2015","property":"","parish":"","notice_refs":""},{"registration_no":172220,"timestamp":"2015-02-06T06:30:48.632663","notice":"","coded_name":"NESNAHIGIULE","type":"WO(B)","county":0,"date":"2011-12-04","remainder_name":"CATHARIN","complex_name":"","hex_code":"29C5","address":"31 LEDNER COURT YK95 5CL WEST VELMA","occupation":"(N/A) MINER","county_text":"","court_info":"WEST MYLENELAND COUNTY COURT 499 OF 2015","property":"","parish":"","notice_refs":""},{"registration_no":13389,"timestamp":"2014-12-22T10:15:15.810242","notice":"","coded_name":"TANSSIEWKCIN","type":"PA(B)","county":0,"date":"2011-02-23","remainder_name":"","complex_name":"","hex_code":"C4","address":"591 WEHNER MOUNTAIN RJ57 1AW PORT NANNIECHESTER","occupation":"(N/A) PRISON OFFICER","county_text":"","court_info":"JESSEFURT COUNTY COURT 74 OF 2015","property":"","parish":"","notice_refs":""},{"registration_no":81595,"timestamp":"2015-06-26T18:51:13.396390","notice":"","coded_name":"TANSSIEWKCIN","type":"WO(B)","county":0,"date":"2011-03-05","remainder_name":"","complex_name":"","hex_code":"C4","address":"591 WEHNER MOUNTAIN RJ57 1AW PORT NANNIECHESTER","occupation":"(N/A) PRISON OFFICER","county_text":"","court_info":"JESSEFURT COUNTY COURT 74 OF 2015","property":"","parish":"","notice_refs":""},{"registration_no":13872,"timestamp":"2015-02-27T15:02:10.862372","notice":"","coded_name":"KECUAPEIMAJS","type":"PA(B)","county":0,"date":"2011-09-17","remainder_name":"JARVI","complex_name":"","hex_code":"26C5","address":"78 ALEXANDRA PLAINS RB64 3LE ELVISVIEW","occupation":"(N/A) PRINTER","county_text":"","court_info":"NEW CYNTHIABURGH COUNTY COURT 31 OF 2015","property":"","parish":"","notice_refs":""},{"registration_no":666840,"timestamp":"2015-02-23T08:06:11.585663","notice":"","coded_name":"KECUAPEIMAJS","type":"WO(B)","county":0,"date":"2011-10-07","remainder_name":"JARVI","complex_name":"","hex_code":"26C5","address":"78 ALEXANDRA PLAINS RB64 3LE ELVISVIEW","occupation":"(N/A) PRINTER","county_text":"","court_info":"NEW CYNTHIABURGH COUNTY COURT 31 OF 2015","property":"","parish":"","notice_refs":""},{"registration_no":983645,"timestamp":"2015-06-27T19:09:17.516140","notice":"","coded_name":"YENEEFEELIAH","type":"PA(B)","county":0,"date":"2011-01-26","remainder_name":"MAYMIE","complex_name":"","hex_code":"26C6","address":"49 HOWELL BROOK VH12 3AR SCHINNERFURT","occupation":"(N/A) PRINTER","county_text":"","court_info":"NEW CARA COUNTY COURT 711 OF 2015","property":"","parish":"","notice_refs":""},{"registration_no":472525,"timestamp":"2015-07-11T12:14:02.295515","notice":"","coded_name":"YENEEFEELIAH","type":"WO(B)","county":0,"date":"2011-02-07","remainder_name":"MAYMIE","complex_name":"","hex_code":"26C6","address":"49 HOWELL BROOK VH12 3AR SCHINNERFURT","occupation":"(N/A) PRINTER","county_text":"","court_info":"NEW CARA COUNTY COURT 711 OF 2015","property":"","parish":"","notice_refs":""},{"registration_no":638860,"timestamp":"2015-07-08T06:33:22.635656","notice":"","coded_name":"LETTILBELACR","type":"PA(B)","county":0,"date":"2011-05-30","remainder_name":"CHESTE","complex_name":"","hex_code":"27C5","address":"793 ZIEMANN LOCKS OM80 5JU CHAMPLINMOUTH","occupation":"(N/A) HEALTH VISITOR","county_text":"","court_info":"SOUTH ERICSIDE COUNTY COURT 271 OF 2015","property":"","parish":"","notice_refs":""},{"registration_no":161194,"timestamp":"2015-08-31T23:02:57.390954","notice":"","coded_name":"LETTILBELACR","type":"WO(B)","county":0,"date":"2011-06-15","remainder_name":"CHESTE","complex_name":"","hex_code":"27C5","address":"793 ZIEMANN LOCKS OM80 5JU CHAMPLINMOUTH","occupation":"(N/A) HEALTH VISITOR","county_text":"","court_info":"SOUTH ERICSIDE COUNTY COURT 271 OF 2015","property":"","parish":"","notice_refs":""},{"registration_no":916370,"timestamp":"2015-09-28T15:26:23.694316","notice":"","coded_name":"ADNALBECIENR","type":"PA(B)","county":0,"date":"2011-09-24","remainder_name":"BE","complex_name":"","hex_code":"C8","address":"56 HACKETT BURGS DC63 5EB LEASHIRE  392 QUIGLEY STATION JN86 0UP DORCASBOROUGH","occupation":"(N/A) RESEARCHER","county_text":"","court_info":"LIZETHPORT COUNTY COURT 986 OF 2015","property":"","parish":"","notice_refs":""},{"registration_no":907168,"timestamp":"2015-03-08T16:54:25.438259","notice":"","coded_name":"ADNALBECIENR","type":"WO(B)","county":0,"date":"2011-10-12","remainder_name":"BE","complex_name":"","hex_code":"C8","address":"56 HACKETT BURGS DC63 5EB LEASHIRE  392 QUIGLEY STATION JN86 0UP DORCASBOROUGH","occupation":"(N/A) RESEARCHER","county_text":"","court_info":"LIZETHPORT COUNTY COURT 986 OF 2015","property":"","parish":"","notice_refs":""},{"registration_no":226972,"timestamp":"2015-11-05T08:14:56.322234","notice":"","coded_name":"NNAMTUGANNAS","type":"PA(B)","county":0,"date":"2011-09-03","remainder_name":"DOMINGORO","complex_name":"","hex_code":"27C7","address":"47 RIVER MILLS AX67 2LX SANDYFORT  27 MCGLYNN TERRACE GG77 4ER EAST RETHAMOUTH  719 REANNA CIRCLE XO15 0GL DEVYNSTAD","occupation":"(N/A) CHILDCARE WORKER","county_text":"","court_info":"HERZOGSTAD COUNTY COURT 598 OF 2015","property":"","parish":"","notice_refs":""},{"registration_no":931902,"timestamp":"2015-11-18T21:51:24.280253","notice":"","coded_name":"NNAMTUGANNAS","type":"WO(B)","county":0,"date":"2012-03-30","remainder_name":"DOMINGORO","complex_name":"","hex_code":"27C7","address":"47 RIVER MILLS AX67 2LX SANDYFORT  27 MCGLYNN TERRACE GG77 4ER EAST RETHAMOUTH  719 REANNA CIRCLE XO15 0GL DEVYNSTAD","occupation":"(N/A) CHILDCARE WORKER","county_text":"","court_info":"HERZOGSTAD COUNTY COURT 598 OF 2015","property":"","parish":"","notice_refs":""},{"registration_no":433906,"timestamp":"2015-06-21T10:55:42.631539","notice":"","coded_name":"NAISIRAPODLA","type":"PA(B)","county":0,"date":"2012-04-13","remainder_name":"VANESSAOSV","complex_name":"","hex_code":"27C7","address":"709 GRADY CENTER CF54 6BK NEW GIUSEPPEBOROUGH  54 HALVORSON ROADS BE86 6MD EAST EDMONDVIEW  924 STOLTENBERG VIADUCT LX76 2SV SOUTH LUCIO","occupation":"(N/A) PORTER","county_text":"","court_info":"KLINGVILLE COUNTY COURT 815 OF 2015","property":"","parish":"","notice_refs":""},{"registration_no":885083,"timestamp":"2015-05-26T22:33:31.741739","notice":"","coded_name":"NAISIRAPODLA","type":"WO(B)","county":0,"date":"2012-01-12","remainder_name":"VANESSAOSV","complex_name":"","hex_code":"27C7","address":"709 GRADY CENTER CF54 6BK NEW GIUSEPPEBOROUGH  54 HALVORSON ROADS BE86 6MD EAST EDMONDVIEW  924 STOLTENBERG VIADUCT LX76 2SV SOUTH LUCIO","occupation":"(N/A) PORTER","county_text":"","court_info":"KLINGVILLE COUNTY COURT 815 OF 2015","property":"","parish":"","notice_refs":""},{"registration_no":338757,"timestamp":"2015-07-12T08:14:06.889200","notice":"","coded_name":"SDLONYERRENR","type":"PA(B)","county":0,"date":"2012-01-25","remainder_name":"WE","complex_name":"","hex_code":"C6","address":"925 AMIRA MISSION VD16 1WS SPORERSHIRE  369 WARD SPRING DU81 2HX NORTH JOHATHANHAVEN  37 HILPERT TRAIL HO11 8JX OWENFORT  104 ROSALIND GREENS FO42 7HW HILPERTPORT","occupation":"(N/A) IMMIGRATION OFFICER","county_text":"","court_info":"MILLSHAVEN COUNTY COURT 766 OF 2015","property":"","parish":"","notice_refs":""},{"registration_no":289970,"timestamp":"2015-07-15T13:56:58.864410","notice":"","coded_name":"SDLONYERRENR","type":"WO(B)","county":0,"date":"2011-10-17","remainder_name":"WE","complex_name":"","hex_code":"C6","address":"925 AMIRA MISSION VD16 1WS SPORERSHIRE  369 WARD SPRING DU81 2HX NORTH JOHATHANHAVEN  37 HILPERT TRAIL HO11 8JX OWENFORT  104 ROSALIND GREENS FO42 7HW HILPERTPORT","occupation":"(N/A) IMMIGRATION OFFICER","county_text":"","court_info":"MILLSHAVEN COUNTY COURT 766 OF 2015","property":"","parish":"","notice_refs":""},{"registration_no":132932,"timestamp":"2015-03-03T10:17:06.113341","notice":"","coded_name":"EDNUKATTESOR","type":"PA(B)","county":0,"date":"2012-06-16","remainder_name":"GUADALUPE","complex_name":"","hex_code":"29C7","address":"894 ARNO MEADOWS OL50 7AR LAKE ALETHA  358 SAVANNA PINES PP33 4QS SIENNALAND  984 FREDA PINE UL44 2GJ NEW JOY  94 JOHNS NECK DW57 9CT DREWHAVEN  431 BRAKUS INLET DN88 0OY EAST HILLARD","occupation":"(N/A) BUILDING LABOURER","county_text":"","court_info":"FLAVIOBURGH COUNTY COURT 762 OF 2015","property":"","parish":"","notice_refs":""},{"registration_no":916061,"timestamp":"2015-06-28T03:48:45.645798","notice":"","coded_name":"EDNUKATTESOR","type":"WO(B)","county":0,"date":"2013-01-02","remainder_name":"GUADALUPE","complex_name":"","hex_code":"29C7","address":"894 ARNO MEADOWS OL50 7AR LAKE ALETHA  358 SAVANNA PINES PP33 4QS SIENNALAND  984 FREDA PINE UL44 2GJ NEW JOY  94 JOHNS NECK DW57 9CT DREWHAVEN  431 BRAKUS INLET DN88 0OY EAST HILLARD","occupation":"(N/A) BUILDING LABOURER","county_text":"","court_info":"FLAVIOBURGH COUNTY COURT 762 OF 2015","property":"","parish":"","notice_refs":""},{"registration_no":907051,"timestamp":"2015-03-17T16:54:04.617658","notice":"","coded_name":"SKRAMIASIASI","type":"PA(B)","county":0,"date":"2013-02-13","remainder_name":"ELO","complex_name":"","hex_code":"26C4","address":"744 ROZELLA CROSSING GT61 4VG WEST KEN  657 ROHAN SUMMIT HD90 2GD QUITZONBURY  460 NORRIS GREEN KJ30 2CU JOVANYBOROUGH  477 CLARK BRANCH VB53 9SK SCOTTIELAND  325 IMOGENE CRESCENT TN92 6RP SOUTH RHIANNAFURT","occupation":"(N/A) HOUSEKEEPER","county_text":"","court_info":"RUBYEBURGH COUNTY COURT 265 OF 2015","property":"","parish":"","notice_refs":""},{"registration_no":635364,"timestamp":"2015-10-09T20:01:11.370305","notice":"","coded_name":"SKRAMIASIASI","type":"WO(B)","county":0,"date":"2013-02-03","remainder_name":"ELO","complex_name":"","hex_code":"26C4","address":"744 ROZELLA CROSSING GT61 4VG WEST KEN  657 ROHAN SUMMIT HD90 2GD QUITZONBURY  460 NORRIS GREEN KJ30 2CU JOVANYBOROUGH  477 CLARK BRANCH VB53 9SK SCOTTIELAND  325 IMOGENE CRESCENT TN92 6RP SOUTH RHIANNAFURT","occupation":"(N/A) HOUSEKEEPER","county_text":"","court_info":"RUBYEBURGH COUNTY COURT 265 OF 2015","property":"","parish":"","notice_refs":""},{"registration_no":994769,"timestamp":"2015-08-06T14:25:00.111360","notice":"","coded_name":"REGNIERNUJRA","type":"PA(B)","county":0,"date":"2013-01-12","remainder_name":"IGNACIO","complex_name":"","hex_code":"27C5","address":"971 DARE LANDING VG42 0QR IRVINGBERG  914 AUFDERHAR RUE TG32 0RM EICHMANNTON  84 ALEJANDRIN DRIVE VJ37 5GF WEST LULAFORT  98 DELMER FORKS IK46 1TL EAST DONNA  148 LESLIE TRAFFICWAY EA37 9OI SOUTH OMARI","occupation":"(N/A) T/A VILLATOM","county_text":"","court_info":"TREVIONFORT COUNTY COURT 529 OF 2015","property":"","parish":"","notice_refs":""},{"registration_no":776327,"timestamp":"2015-06-14T02:46:28.927656","notice":"","coded_name":"REGNIERNUJRA","type":"WO(B)","county":0,"date":"2013-01-24","remainder_name":"IGNACIO","complex_name":"","hex_code":"27C5","address":"971 DARE LANDING VG42 0QR IRVINGBERG  914 AUFDERHAR RUE TG32 0RM EICHMANNTON  84 ALEJANDRIN DRIVE VJ37 5GF WEST LULAFORT  98 DELMER FORKS IK46 1TL EAST DONNA  148 LESLIE TRAFFICWAY EA37 9OI SOUTH OMARI","occupation":"(N/A) T/A VILLATOM AS CHILDMINDER","county_text":"","court_info":"TREVIONFORT COUNTY COURT 529 OF 2015","property":"","parish":"","notice_refs":""},    

    {"timestamp": "2014-11-26T22:11:53.068832", "registration_no":95098, "notice": "P", "coded_name": "REDIENHCSATN", "county":255, "date": "2014-12-24", "type": "PA", "remainder_name": "VICE", "hex_code": "C7", "complex_name": "", "address": "", "occupation": "", "county_text": "DEVON", "court_info": "", "property": "JUSINE POINTES LINCOLNSHIRE", "parish": "LINCOLNSHIRE", "notice_refs": ""},
    {"timestamp": "2010-05-13T22:12:13.832491", "registration_no":95098, "notice": "", "coded_name": "REDEORHCSSIN", "county":255, "date": "2010-06-14", "type": "WO(B)", "remainder_name": "DEN", "hex_code": "C6", "complex_name": "", "address": "IVY HOUSE KLEINTON NEWPORT TD78 89D SOMERSET", "occupation": "(N/A) UNEMPLOYED", "county_text": "", "court_info": "BRIDGESTART COUNTY COURT NO 567 OF 2010", "property": "", "parish": "", "notice_refs": ""},
    {"timestamp": "2014-11-05T22:11:32.431238", "registration_no":57019, "notice": "P", "coded_name": "GNALNOTLAWAZ", "county":28, "date": "2014-12-01", "type": "D(III)", "remainder_name": "ELI", "hex_code": "25C6", "complex_name": "", "address": "", "occupation": "", "county_text": "", "court_info": "", "property": "LAND FORMERLY FORMING PART OF LAUREN PINES ADDISON ML23 2QX", "parish": "BRIZZL", "notice_refs": ""},
    {"timestamp": "2014-07-21T22:17:54.664703", "registration_no":18530, "notice": "", "coded_name": "MUANGREBNAIT", "county":235, "date": "2014-08-22", "type": "F", "remainder_name": "SEBAS", "hex_code": "C9", "complex_name": "", "address": "", "occupation": "", "county_text": "", "court_info": "PART CAN 65670 REGD 2014-12-24 SO FAR ONLY AS IT RELATES TO THE AREA MARKED RED ON THE PLAN ANNEXED HERETO AS DESC ON APPN TO CANCEL", "property": "61 SHIELDS JUNCTION THEILFURT MI23 1SD", "parish": "KINGSTON", "notice_refs": ""},
    {"timestamp": "2005-06-02T22:33:55.400312", "registration_no":30563, "notice": "", "coded_name": "REGEOHDYOLFY", "county":109, "date": "2005-07-29", "type": "C(IV)", "remainder_name": "ROCKYZACHER", "hex_code": "2527C5", "complex_name": "", "address": "", "occupation": "", "county_text": "", "court_info": "PART CAN 42293 REGD 2014-12-24 SO FAR ONLY AS IT RELATES TO LAND AT OTHO ROAD THIRSK SHOWN EDGED RED ON THE PLAN ATTACHED AS DESC ON APPN TO CANCEL", "property": "LAND AT MURRAY ROAD AS DEFINED IN SCHEDULE 5 AND SHOWN ON PLAN 1 TO THE OPTION AGREEMENT DATED 2015-08-05", "parish": "POWYS", "notice_refs": ""},
    {"timestamp": "2014-10-08T22:11:19.665507", "registration_no":94160, "notice": "", "coded_name": "YDARGTTEMME", "county":173, "date": "2014-11-16", "type": "B", "remainder_name": "", "hex_code": "C6", "complex_name": "", "address": "", "occupation": "", "county_text": "", "court_info": "SHORT DESCRIPTION RECTIFIED FROM 31 THEA STREET MELVIN JH65 6FV BY 80641 REGD 2014-11-25", "property": "25 VERNA STREET MARBOROUGH RP87 8DJ", "parish": "POWYS", "notice_refs": ""},
    {"timestamp": "2014-08-21T22:11:14.205658", "registration_no":59601, "notice": "", "coded_name": "REROBNETNIUQ", "county":124, "date": "2014-09-16", "type": "C(III)", "remainder_name": "PRISCILLA", "hex_code": "29C7", "complex_name": "", "address": "", "occupation": "", "county_text": "", "court_info": "NAME PREVIOUSLY REGISTERED AS DARION GOODWIN UNDER 27600 REGD 2014-09-12", "property": "LAND AND BUILDINGS AT WADE FARM ODELL LANE", "parish": "KENT", "notice_refs": ""},
    {"timestamp": "2014-08-11T22:17:03.973823", "registration_no":27600, "notice": "", "coded_name": "NIWDOOGECNER", "county":124, "date": "2014-09-12", "type": "C(III)", "remainder_name": "DARIONLAW", "hex_code": "26C8", "complex_name": "", "address": "", "occupation": "", "county_text": "", "court_info": "NAME RECTIFIED TO XXX BY 59601 REGD 2014-09-16 & CHARGEE RECTIFIED FROM XXX TO XXXX BY 59601 REGD 2014-09-16", "property": "LAND AND BUILDINGS AT WADE FARM ODELL LANE", "parish": "KENT", "notice_refs": ""},
    {"timestamp": "2014-10-09T22:11:19.169128", "registration_no":23335, "notice": "", "coded_name": "NOSMAS", "county":255, "date": "2014-11-03", "type": "WO", "remainder_name": "", "hex_code": "", "complex_name": "", "address": "", "occupation": "", "county_text": "ESSEX", "court_info": "RENEWAL OF 156842 REGD 2010-11-30 WHICH RENEWED 197644 REGD 2005-12-09 WHICH RENEWED 1234 REGD 2001-02-18 WHICH RENEWED 6254 REGD 1995-04-11", "property": "61 EMARD LAND  WEST TYRELL", "parish": "SOUTHAMPTON", "notice_refs": ""},
    {"timestamp": "1995-02-02T18:31:51.953671", "registration_no":6254, "notice": "", "coded_name": "LLLIHNOTNATS", "county":109, "date": "1995-03-17", "type": "C(IV)", "remainder_name": "JEFFERY", "hex_code": "27C7", "complex_name": "", "address": "", "occupation": "", "county_text": "", "court_info": "", "property": "35 M7 OF LAND ADJOINING C23413 ART ROAD TONEY", "parish": "BEDFORD", "notice_refs": ""},
    {"timestamp": "2013-04-22T22:26:03.061893", "registration_no":57332, "notice": "", "coded_name": "HCIERNEDIEHE", "county":244, "date": "2013-05-14", "type": "F", "remainder_name": "THEODOR", "hex_code": "C8", "complex_name": "", "address": "", "occupation": "", "county_text": "", "court_info": "RENEWAL OF 32391 REGD 2012-11-22", "property": "432 GREEN WAYS H76 8JH", "parish": "DORSET", "notice_refs": ""},
    {"timestamp": "2012-10-31T22:11:05.476095", "registration_no":32391, "notice": "", "coded_name": "HCIERNEDIEHE", "county":244, "date": "2012-11-22", "type": "F", "remainder_name": "THEODOR", "hex_code": "C8", "complex_name": "", "address": "", "occupation": "", "county_text": "", "court_info": "RENEWED BY 57332 REGD 2013-05-14", "property": "432 GREEN WAYS H76 8JH", "parish": "DORSET", "notice_refs": ""},
    {"timestamp": "1991-08-06T01:44:20.357817", "registration_no":18530, "notice": "", "coded_name": "SPLACETONSH", "county":82, "date": "1979-02-16", "type": "C(IV)", "remainder_name": "IRE", "hex_code": "", "complex_name": "+SOUTH PLACETONSHIRE+DISTRICT COUNCIL", "address": "", "occupation": "", "county_text": "", "court_info": "", "property": "REFECTORY PREMISES SITUATE ON THE PROMENADE LEADING FROM FREDE ROAD TO THE SOUTH AND BEHIND AND ABUTTING ON TO THE WEST BEACH DRADEN", "parish": "DRADEN", "notice_refs": ""},
    {"timestamp": "1991-08-06T01:44:20.359679", "registration_no":18530, "notice": "", "coded_name": "SPLACETONSH", "county":127, "date": "1979-02-16", "type": "C(IV)", "remainder_name": "IRE", "hex_code": "", "complex_name": "+SOUTH PLACETONSHIRE+DISTRICT COUNCIL", "address": "", "occupation": "", "county_text": "", "court_info": "", "property": "REFECTORY PREMISES SITUATE ON THE PROMENADE LEADING FROM FREDE ROAD TO THE SOUTH AND BEHIND AND ABUTTING ON TO THE WEST BEACH DRADEN", "parish": "DRADEN", "notice_refs": ""},
    {"timestamp": "1991-08-06T01:49:41.270978", "registration_no":30563, "notice": "", "coded_name": "F91041E800000000000000F3", "county":34, "date": "1991-07-05", "type": "F", "remainder_name": "", "hex_code": "", "complex_name": "BORERBERG VISCOUNT", "address": "", "occupation": "", "county_text": "", "court_info": "", "property": "FAYTON", "parish": "NEWPORT", "notice_refs": ""},
    {"timestamp": "1991-08-06T01:48:13.580405", "registration_no":32391, "notice": "", "coded_name": "F91044F000000000000000F3", "county":181, "date": "1931-09-10", "type": "D(II)", "remainder_name": "", "hex_code": "", "complex_name": "MOCKVILLE BISHOP OF", "address": "", "occupation": "2ND EARL", "county_text": "", "court_info": "", "property": "", "parish": "NOTTINGHAMSHIRE", "notice_refs": ""},
    {"timestamp": "1993-07-05T01:45:41.515130", "registration_no":25877, "notice": "", "coded_name": "MAHARGOMIXAM", "county":94, "date": "1968-12-25", "type": "D(II)", "remainder_name": "THEO", "hex_code": "24C6", "complex_name": "", "address": "", "occupation": "", "county_text": "", "court_info": "", "property": "19 TYSON COURT", "parish": "SWANSEA", "notice_refs": ""},
    {"timestamp": "1993-07-05T01:42:57.987412", "registration_no":151725, "notice": "", "coded_name": "IBOCAJREHPOT", "county":55, "date": "1961-12-31", "type": "D(II)", "remainder_name": "BRADYCRIS", "hex_code": "25CA", "complex_name": "", "address": "EAST LURLINE NOTTS.", "occupation": "", "county_text": "", "court_info": "VARIOUS PART CANS APPLY DETAILS OF WHICH WILL BE SUPPLIED ON REQUEST", "property": "", "parish": "THE VALE OF GLAMORGAN", "notice_refs": ""}]
